dynaform/__init__.py
dynaform/admin.py
dynaform/apps.py
dynaform/const.py
dynaform/forms.py
dynaform/models.py
dynaform/service.py
dynaform/urls.py
dynaform/views.py
dynaform/migrations/0001_initial.py
dynaform/migrations/__init__.py
dynaform/templates/dynaform/base.html
dynaform/templates/dynaform/dynaform-data-edit.html
dynaform/templates/dynaform/dynaform-data-list.html
dynaform/templates/dynaform/link-to-dynaform-data-delete.html
dynaform/templates/dynaform/link-to-dynaform-data-edit.html
dynaform/templatetags/__init__.py
dynaform/templatetags/dynaform.py
settings/__init__.py
settings/base.py
settings/dummy.py
settings/postgres.py
django_dynaform-0.1.2.dist-info/METADATA
django_dynaform-0.1.2.dist-info/WHEEL
django_dynaform-0.1.2.dist-info/top_level.txt
django_dynaform-0.1.2.dist-info/RECORD
